model/__init__.py
model/mspca.py
mspca/__init__.py
mspca/mspca.py
mspca-0.0.4.dist-info/LICENSE
mspca-0.0.4.dist-info/METADATA
mspca-0.0.4.dist-info/WHEEL
mspca-0.0.4.dist-info/top_level.txt
mspca-0.0.4.dist-info/RECORD
