Metadata-Version: 2.1
Name: mspca
Version: 0.0.4
Summary: Multiscale Principal Component Analysis Algorithm
Home-page: https://github.com/khusss/mspca
Author: Heeyu Kim
Author-email: khudd@naver.com
License: UNKNOWN
Platform: UNKNOWN
Classifier: Programming Language :: Python :: 3
Classifier: License :: OSI Approved :: MIT License
Classifier: Operating System :: OS Independent
Requires-Dist: PyWavelets
